sizecheck.py
sizecheck-0.2.0.dist-info/METADATA
sizecheck-0.2.0.dist-info/WHEEL
sizecheck-0.2.0.dist-info/top_level.txt
sizecheck-0.2.0.dist-info/RECORD
