Metadata-Version: 2.4
Name: sizecheck
Version: 0.2.0
Summary: Runtime shape validation for size-annotated Python code
License: MIT
Project-URL: Homepage, https://github.com/samanklesaria/sizecheck
Project-URL: Repository, https://github.com/samanklesaria/sizecheck
Project-URL: Issues, https://github.com/samanklesaria/sizecheck/issues
Classifier: Development Status :: 3 - Alpha
Classifier: Intended Audience :: Developers
Classifier: License :: OSI Approved :: MIT License
Classifier: Programming Language :: Python :: 3
Classifier: Programming Language :: Python :: 3.8
Classifier: Programming Language :: Python :: 3.9
Classifier: Programming Language :: Python :: 3.10
Classifier: Programming Language :: Python :: 3.11
Classifier: Topic :: Scientific/Engineering :: Artificial Intelligence
Classifier: Topic :: Software Development :: Libraries :: Python Modules
Requires-Python: >=3.8
Provides-Extra: test
Requires-Dist: torch>=1.8.0; extra == "test"
Requires-Dist: pytest>=6.0; extra == "test"
Requires-Dist: numpy>=1.24.4; extra == "test"
